fetchfox_sdk/__init__.py
fetchfox_sdk/api.py
fetchfox_sdk/configure.py
fetchfox_sdk/crawl.py
fetchfox_sdk/extract.py
fetchfox_sdk/fox.py
fetchfox_sdk/scrape.py
fetchfox_sdk-1.0.1.dist-info/METADATA
fetchfox_sdk-1.0.1.dist-info/WHEEL
fetchfox_sdk-1.0.1.dist-info/top_level.txt
fetchfox_sdk-1.0.1.dist-info/RECORD
