Metadata-Version: 2.4
Name: fetchfox-sdk
Version: 1.0.1
Summary: Python SDK for the FetchFox API
Author-email: FetchFox <dev@fetchfoxai.com>
License: MIT
Project-URL: Homepage, https://fetchfox.ai
Project-URL: Source, https://github.com/fetchfox/fetchfox-sdk-python
Requires-Python: >=3.9
Requires-Dist: httpx>=0.27.0
Requires-Dist: pytest-asyncio>=1.1.0
Provides-Extra: dev
Requires-Dist: pytest>=8.3.4; extra == "dev"
